pythondelegate/__init__.py
pythondelegate/actions.py
pythondelegate/delegate.py
pythondelegate/event_args.py
pythondelegate/event_handler.py
pythondelegate/funcs.py
pythondelegate-0.1.0.dist-info/LICENSE
pythondelegate-0.1.0.dist-info/METADATA
pythondelegate-0.1.0.dist-info/WHEEL
pythondelegate-0.1.0.dist-info/top_level.txt
pythondelegate-0.1.0.dist-info/RECORD
