Metadata-Version: 2.1
Name: pythondelegate
Version: 0.1.0
Summary: A CSharp like delegate implement for Python
Author: Eterance
Keywords: Delegate,Callback
Classifier: Programming Language :: Python :: 3
Classifier: License :: OSI Approved :: MIT License
Classifier: Operating System :: OS Independent
Requires-Python: >=3.8
License-File: LICENSE
